threatbus_zmq_app/__init__.py
threatbus_zmq_app/message_mapping.py
threatbus_zmq_app/plugin.py
threatbus_zmq_app/test_message_mapping.py
threatbus_zmq_app-2021.7.29.dist-info/METADATA
threatbus_zmq_app-2021.7.29.dist-info/WHEEL
threatbus_zmq_app-2021.7.29.dist-info/entry_points.txt
threatbus_zmq_app-2021.7.29.dist-info/top_level.txt
threatbus_zmq_app-2021.7.29.dist-info/RECORD
