Metadata-Version: 2.1
Name: threatbus-zmq-app
Version: 2021.7.29
Summary: A plugin to connect apps via ZeroMQ.
Home-page: https://github.com/tenzir/threatbus
Author: Tenzir
Author-email: engineering@tenzir.com
License: BSD 3-clause
Keywords: zeromq,zmq,threatbus,Threat Bus,threat intelligence,TI,TI dissemination
Platform: UNKNOWN
Classifier: Development Status :: 4 - Beta
Classifier: Environment :: Plugins
Classifier: License :: OSI Approved :: BSD License
Classifier: Operating System :: MacOS :: MacOS X
Classifier: Operating System :: POSIX :: Linux
Classifier: Programming Language :: Python :: 3
Classifier: Topic :: Scientific/Engineering :: Information Analysis
Classifier: Topic :: Scientific/Engineering :: Interface Engine/Protocol Translator
Classifier: Topic :: Security
Classifier: Topic :: Software Development :: Object Brokering
Classifier: Topic :: System :: Distributed Computing
Requires-Python: >=3.7
Requires-Dist: pyzmq (>=19)
Requires-Dist: python-dateutil (>=2.8.1)
Requires-Dist: stix2 (<3.0,>=2.1)
Requires-Dist: threatbus (>=2021.5.27)
